cairoo/__init__.py
cairoo/main.py
cairoo/setup.py
draw/__init__.py
draw/main.py
draw/setup.py
cairoo-0.0.5.dist-info/METADATA
cairoo-0.0.5.dist-info/WHEEL
cairoo-0.0.5.dist-info/top_level.txt
cairoo-0.0.5.dist-info/RECORD
