Metadata-Version: 2.1
Name: cairoo
Version: 0.0.5
Summary: easy cairocffi wrapper
Home-page: UNKNOWN
Author: Lewis Morris
Author-email: lewis.morris@gmail.com
License: MIT
Platform: UNKNOWN
